musx2mxl/__init__.py
musx2mxl/chord-suffixes.json
musx2mxl/converter.py
musx2mxl/helper.py
musx2mxl/instruments.json
musx2mxl/musx2mxl.py
musx2mxl/musx2mxl_gui.py
musx2mxl-0.2.9.dist-info/LICENSE
musx2mxl-0.2.9.dist-info/METADATA
musx2mxl-0.2.9.dist-info/WHEEL
musx2mxl-0.2.9.dist-info/entry_points.txt
musx2mxl-0.2.9.dist-info/top_level.txt
musx2mxl-0.2.9.dist-info/RECORD
