Metadata-Version: 2.1
Name: musx2mxl
Version: 0.2.9
Summary: UNKNOWN
Home-page: UNKNOWN
License: UNKNOWN
Platform: UNKNOWN
Classifier: Programming Language :: Python :: 3
Classifier: License :: OSI Approved :: MIT License
Requires-Python: >=3.9
License-File: LICENSE
Requires-Dist: lxml (~=4.8.0)
Requires-Dist: tkinterdnd2 (~=0.4.2)
